surreal/__init__.py
surreal/client.py
surreal/exceptions.py
surreal/utils/__init__.py
surreal/utils/event_listener.py
surreal/utils/wrap_request.py
surreal_db_python-1.0.2.dist-info/METADATA
surreal_db_python-1.0.2.dist-info/WHEEL
surreal_db_python-1.0.2.dist-info/top_level.txt
surreal_db_python-1.0.2.dist-info/RECORD
