Metadata-Version: 2.1
Name: surreal-db-python
Version: 1.0.2
Summary: Python client for the Surreal Database (Websocket not supported)
Home-page: https://github.com/timelessnesses/surreal-db-python
Author: Rukchad Wongprayoon
Author-email: contact@rukchadisa.live
License: UNKNOWN
Platform: UNKNOWN
Classifier: Programming Language :: Python :: 3
Classifier: Development Status :: 2 - Pre-Alpha
Classifier: Framework :: AsyncIO
Classifier: Intended Audience :: Developers
Classifier: License :: OSI Approved :: MIT License
Classifier: Natural Language :: English
Classifier: Operating System :: OS Independent
Classifier: Programming Language :: Python
Classifier: Programming Language :: Python :: 3
Classifier: Topic :: Database
Classifier: Typing :: Typed
Requires-Dist: aiohttp
Requires-Dist: requests
Requires-Dist: yarl
Provides-Extra: speed
Requires-Dist: aiohttp[speedups] ; extra == 'speed'
Requires-Dist: orjson ; extra == 'speed'
